{
    "@bugsnag/browser": 1746144,
    "@bugsnag/node": 1726108,
    "@bugsnag/js": 1656795,
    "@bugsnag/core": 1526713,
    "@bugsnag/safe-json-stringify": 1454513,
    "@bugsnag/cuid": 1415498,
    "@bugsnag/plugin-react": 754228,
    "@bugsnag/source-maps": 340935,
    "@buffetjs/styles": 333606,
    "@buffetjs/core": 329603,
    "@buffetjs/icons": 328793,
    "@buffetjs/utils": 326317,
    "@buffetjs/hooks": 325125,
    "@buffetjs/custom": 324776,
    "@bugsnag/plugin-express": 241583,
    "@bugsnag/plugin-console-breadcrumbs": 166400,
    "@bugsnag/plugin-network-breadcrumbs": 166239,
    "@bugsnag/plugin-react-native-unhandled-rejection": 165072,
    "@bugsnag/plugin-react-native-global-error-handler": 164094,
    "@bugsnag/react-native": 161134,
    "@bugsnag/plugin-react-native-client-sync": 158908,
    "@bugsnag/plugin-react-native-event-sync": 158903,
    "@bugsnag/delivery-react-native": 158898,
    "@bugsnag/plugin-react-native-hermes": 158892,
    "@bugsnag/plugin-react-native-session": 158885,
    "@bugsnag/plugin-vue": 133490,
    "@bukhr/base64image": 43485,
    "@bugsnag/plugin-angular": 38403,
    "@bugsnag/plugin-koa": 33735,
    "@builder.io/sdk": 24698,
    "@bull-board/api": 23860,
    "@bull-board/ui": 23616,
    "@builder.io/react": 21820,
    "@bull-board/express": 20683,
    "@bugsnag/plugin-react-navigation": 18791,
    "@bugsnag/plugin-browser-session": 18736,
    "@bugsnag/in-flight": 12083,
    "@bugsnag/plugin-aws-lambda": 11963,
    "@bugsnag/react-native-cli": 10979,
    "@builder.io/widgets": 10657,
    "@builder.io/webcomponents": 8042,
    "@bullhorn/bullhorn-icons": 7878,
    "@builder.io/angular": 6929,
    "@build-tracker/cli": 5923,
    "@bugsnag/expo": 5892,
    "@bugsnag/plugin-expo-device": 5754,
    "@build-tracker/api-client": 5722,
    "@bugsnag/delivery-expo": 5677,
    "@bugsnag/plugin-react-native-connectivity-breadcrumbs": 5660,
    "@bugsnag/plugin-expo-app": 5651,
    "@bugsnag/plugin-react-native-orientation-breadcrumbs": 5622,
    "@bugsnag/plugin-react-native-app-state-breadcrumbs": 5618,
    "@builder.io/email": 4743,
    "@bugfender/rn-bugfender": 4239,
    "@builder.io/shopify": 4149,
    "@bufferapp/ui": 4018,
    "@buildium/theme": 3979,
    "@bufferapp/web-analyze": 2933,
    "@bulb/patterns": 2748,
    "@builder/user-config": 2695,
    "@builder.io/gatsby": 2362,
    "@bufferapp/summary-table": 2356,
    "@bugsnag/plugin-window-unhandled-rejection": 2221,
    "@bufferapp/report": 2182,
    "@builder/app-helpers": 2167,
    "@bugsnag/plugin-window-onerror": 2148,
    "@bull-board/fastify": 2132,
    "@bufferapp/report-list": 2006,
    "@bufferapp/session-manager": 1998,
    "@bufferapp/server-analyze": 1996,
    "@builder/mpa-config": 1944,
    "@bugsnag/plugin-interaction-breadcrumbs": 1929,
    "@bugsnag/plugin-react-native-navigation": 1880,
    "@bugsnag/plugin-node-uncaught-exception": 1838,
    "@bugsnag/plugin-node-surrounding-code": 1785,
    "@bugsnag/plugin-strip-project-root": 1778,
    "@bugsnag/plugin-node-unhandled-rejection": 1771,
    "@builder/babel-preset-ice": 1761,
    "@build-security/react-rbac-ui-manager": 1756,
    "@bulb/eslint-config-bulb": 1687,
    "@builtbypixel/nucleus": 1686,
    "@builtbypixel/plasma": 1674,
    "@bugsnag/plugin-restify": 1521,
    "@bugfender/sdk": 1502,
    "@builder.io/vue": 1468,
    "@bullhorn/bullhorn-types": 1451,
    "@builder.io/react-native": 1358,
    "@bugsnag/electron": 1321,
    "@bugsnag/plugin-electron-app": 1289,
    "@bugsnag/plugin-electron-renderer-event-data": 1280,
    "@bugsnag/plugin-electron-device": 1276,
    "@bugsnag/plugin-electron-preload-error": 1276,
    "@bugsnag/plugin-electron-renderer-strip-project-root": 1273,
    "@bugsnag/plugin-electron-session": 1273,
    "@bugsnag/plugin-electron-process-info": 1271,
    "@bugsnag/plugin-electron-client-state-manager": 1269,
    "@bugsnag/plugin-electron-net-breadcrumbs": 1269,
    "@bugsnag/delivery-electron": 1267,
    "@bugsnag/plugin-electron-ipc": 1266,
    "@bugsnag/plugin-electron-network-status": 1265,
    "@bugsnag/plugin-electron-renderer-client-state-updates": 1265,
    "@bugsnag/plugin-electron-app-breadcrumbs": 1263,
    "@bugsnag/plugin-internal-callback-marker": 1263,
    "@bugsnag/plugin-stackframe-path-normaliser": 1263,
    "@bugsnag/electron-filestore": 1232,
    "@bull-board/koa": 1131,
    "@builder.io/plugin-loader": 1124,
    "@bull-monitor/root": 1098,
    "@bulatdashiev/svelte-slider": 1082,
    "@bufferapp/react-simple-dropdown": 1064,
    "@builder.io/utils": 1052,
    "@bull-monitor/express": 1020,
    "@bufferapp/react-keyframes": 1007,
    "@bugsnag/plugin-simple-throttle": 920,
    "@bufferapp/shutdown-helper": 866,
    "@bufferapp/web-components": 796,
    "@builder/pack": 782,
    "@bugsnag/plugin-navigation-breadcrumbs": 761,
    "@bukinoshita/space": 756,
    "@bugsnag/plugin-strip-query-string": 743,
    "@bufferapp/quick-tips": 730,
    "@bullhorn/dragula": 715,
    "@builder.io/plugin-cloudinary": 711,
    "@bufferapp/stories-summary-table": 710,
    "@bugsounet/google-assistant": 699,
    "@builton/core-sdk": 675,
    "@bugsounet/cast": 662,
    "@bugsnag/delivery-x-domain-request": 639,
    "@bugsnag/plugin-inline-script-content": 639,
    "@bugsnag/delivery-node": 635,
    "@bugsnag/plugin-browser-device": 633,
    "@bugsnag/plugin-browser-context": 629,
    "@bugsnag/delivery-xml-http-request": 625,
    "@bugsnag/plugin-browser-request": 624,
    "@bugsnag/plugin-client-ip": 622,
    "@bugsnag/plugin-node-device": 620,
    "@bugsnag/plugin-contextualize": 617,
    "@bugsnag/plugin-intercept": 616,
    "@bugsnag/plugin-node-in-project": 611,
    "@bugsnag/plugin-server-session": 607,
    "@bufferapp/shopify-totals": 589,
    "@bugsounet/snowboy": 588,
    "@build-tracker/comparator": 579,
    "@bufferapp/react-images-loaded": 578,
    "@bufferapp/shopify-sources": 575,
    "@builder.io/plugin-shopify": 573,
    "@builder.io/forum-tracking": 567,
    "@buggyorg/graphtools": 566,
    "@builder.io/qwik": 566,
    "@bufferapp/stories-daily": 565,
    "@bufferapp/shopify-products": 558,
    "@bugsounet/npmcheck": 555,
    "@bugsounet/screen": 555,
    "@buildout/hot-formula-parser": 546,
    "@bufferapp/publish-store": 545,
    "@bull-board/hapi": 539,
    "@builder/babel-config": 538,
    "@buildertrend/react-number-format": 532,
    "@bukio/brick": 532,
    "@buildo/hophop": 531,
    "@bufferapp/upgrade-to-pro": 529,
    "@bullhorn/taurus": 524,
    "@bufferapp/publish-web": 523,
    "@builder/jest-config": 521,
    "@builder/webpack-config": 520,
    "@builder.io/monorepo": 515,
    "@builder/swc-loader": 514,
    "@buildout/formulajs": 514,
    "@bufferapp/publish-queue": 501,
    "@bufferapp/publish-sent": 489,
    "@build-tracker/types": 480,
    "@bullcode/mobile": 480,
    "@bull-monitor/koa": 468,
    "@build-tracker/formatting": 465,
    "@bugsounet/pir": 464,
    "@build-tracker/build": 461,
    "@bufferapp/publish-server": 453,
    "@builder.io/sqlgenerate": 453,
    "@bufferapp/publish-settings": 452,
    "@bugsounet/internet": 444,
    "@bufferapp/publish-shared-components": 442,
    "@bufferapp/publish-tabs": 430,
    "@builtioflow/connector-builder": 429,
    "@bugsounet/governor": 428,
    "@buildo/bento": 427,
    "@bull-monitor/hapi": 425,
    "@bull-monitor/ui": 424,
    "@bugsounet/cvlc": 423,
    "@builder.io/html-to-figma": 423,
    "@bugsounet/secure-ga-v3": 420,
    "@bugsounet/systemd": 419,
    "@bufferapp/publish-pusher-sync": 418,
    "@bull-monitor/fastify": 418,
    "@builder.io/editor": 417,
    "@bugsounet/google-photos": 416,
    "@bugsounet/node-lpcm16": 414,
    "@builder.io/storybook": 411,
    "@bugsounet/node-buffertomp3": 404,
    "@bugsounet/spotify": 400,
    "@bufferapp/publish-profile-sidebar": 386,
    "@bufferapp/publish-utils": 376,
    "@bufferapp/publish-parsers": 356,
    "@buildingsblock/core": 346,
    "@bufferapp/stories-breakdown": 334,
    "@bufferapp/recent-posts": 323,
    "@build-script/builder": 323,
    "@builder/vite-service": 316,
    "@builder.io/editor-client": 313,
    "@buildingcompanion/salesmanago": 310,
    "@bullit/pets-js-sdk": 308,
    "@bufferapp/top-posts-table": 301,
    "@builder/html-generator": 301,
    "@bugsnag/plugin-app-duration": 298,
    "@bugsworld85/neocomponents": 297,
    "@builtwithluv/mockit": 297,
    "@builder.io/mobx-state-tree": 296,
    "@builder/app-templates": 293,
    "@buildium/angular-elements": 291,
    "@buggyorg/buggy": 288,
    "@buildit/gravity-ui-web": 282,
    "@builder.io/sdk-react-native": 279,
    "@build-tracker/server": 278,
    "@build-tracker/app": 276,
    "@bugsounet/porcupine": 274,
    "@builder.io/ts-transform-optional-chaining": 267,
    "@buildium/angular-redux": 267,
    "@builderx/utils": 264,
    "@buggyorg/resolve": 263,
    "@builder.io/cli": 259,
    "@builder/exports-field-webpack-plugin": 257,
    "@bukio/components": 256,
    "@bufferapp/unauthorized-redirect": 255,
    "@bugsplat/ng-animated-counter": 254,
    "@bufferapp/rpc-worker": 253,
    "@buggyorg/graphify": 248,
    "@bufferapp/reach-comparison-chart": 245,
    "@bufferapp/publish-preferences": 243,
    "@bufferapp/publish-upgrade-modal": 231,
    "@bug-crusher/client-js": 231,
    "@bufferapp/publish-modals": 226,
    "@buildit/storybook-addon-blabbr": 226,
    "@builder.io/plugin-dynamic-dropdown": 214,
    "@builder.io/worker-loader": 208,
    "@builder.io/rollup-plugin-node-resolve-browser": 201,
    "@buggyorg/component-library": 192,
    "@buggyorg/lisgy": 192,
    "@builder.io/block-publish": 188,
    "@build-script/typescript-transformer-dual-package": 187,
    "@build-script/export-all-in-one": 186,
    "@build-script/rush-tools": 183,
    "@builder.io/mitosis": 173,
    "@bugfix2019/react-test-component": 168,
    "@build-in-the-cloud/ssl-checker-cdk": 167,
    "@buildium/angular-ui": 165,
    "@buildo/create-bento-app": 161,
    "@bufferapp/stripe": 160,
    "@build-tracker/plugin-with-mariadb": 160,
    "@buildmotion/security": 158,
    "@bufferapp/publish-i18n": 157,
    "@build-tracker/plugin-with-postgres": 156,
    "@buildit/storybook-addon-versions": 155,
    "@bugsplat/ngb-filterable-dropdown": 154,
    "@buggyorg/gogen": 152,
    "@build-script/export-all-in-one-inject": 145,
    "@build-script/poormans-package-change": 145,
    "@build-script/single-dog": 145,
    "@build-script/typescript-transformer-import-commonjs": 143,
    "@buggyorg/dupjoin": 140,
    "@bullhorn/bullhorn-cli": 140,
    "@build-script/rollup-plugin-module-import-dew": 139,
    "@builder.io/commerce-plugin-tools": 136,
    "@buildium/moment": 136,
    "@bullcode/web": 134,
    "@build-script/single-dog-asset": 131,
    "@bugsounet/pronote-api": 130,
    "@build-script/typescript-transformer-resolve-info": 130,
    "@builder.io/plugin-async-dropdown": 130,
    "@buildit/gravity-particles": 130,
    "@buildtip/create-web-app": 130,
    "@build-tracker/plugin-with-mysql": 128,
    "@build-script/typescript-transformer-common": 123,
    "@bufferapp/publish-routes": 122,
    "@bugout/bugout-js": 122,
    "@builtwithluv/testy": 122,
    "@buildit/gravity-ui-sass": 120,
    "@build-script/dual-package-runtime": 119,
    "@bugsnag/plugin-electron-client-state-persistence": 118,
    "@building-block/xhr-fetch": 116,
    "@buildium/angular-docs": 116,
    "@build-script/typescript-transformer-static-resolve": 115,
    "@builder.io/mitosis-cli": 115,
    "@buibis/code-config": 114,
    "@builder.io/amp": 114,
    "@buildit/gravy": 113,
    "@buggyorg/npg-port-remodeler": 112,
    "@bug-hunt/bughunt.baseevents-backend": 110,
    "@bugsnag/plugin-electron-power-monitor-breadcrumbs": 110,
    "@bugsnag/plugin-electron-screen-breadcrumbs": 110,
    "@builder.io/plugin-swell": 108,
    "@buggyorg/graphlib2kgraph": 106,
    "@building-block/track-progress": 104,
    "@builderbuch/core": 100,
    "@buggyorg/dynatype-network-graph": 99,
    "@bullrunfinance/uikit": 99,
    "@buggyorg/rewrite": 98,
    "@buildeazy-gmbh/visualizer": 98,
    "@buggie/core": 97,
    "@build-script/gulp-chain-simplify": 97,
    "@buildtheearth/bot-logger": 97,
    "@buggie/device-info": 96,
    "@buggyorg/functional": 95,
    "@builderbuch/cli": 95,
    "@buggyorg/typify": 93,
    "@builton/node-sdk": 92,
    "@bufferapp/redux-hover": 90,
    "@bugsounet/md5": 90,
    "@build-tracker/api-errors": 90,
    "@buildersstudio/builders-scripts": 89,
    "@buggie/network-debugger": 87,
    "@bugout/humbug": 87,
    "@bullhorn/bullhornjs": 87,
    "@buildmotion/foundation": 86,
    "@builat/printscreen": 84,
    "@bulentv/smb2": 82,
    "@bufferapp/utms": 81,
    "@buggyorg/generics": 80,
    "@buggyorg/portgraph2kgraph": 79,
    "@buildo/formo": 79,
    "@bulbariss/ui": 76,
    "@buibis/buibis-version": 75,
    "@buildit/job-listings": 73,
    "@builder.io/memsource-connector": 72,
    "@bugsounet/test-md5": 71,
    "@build-tracker/fixtures": 71,
    "@bugsplat/stack-converter": 70,
    "@bugsplat/symbol-upload": 70,
    "@build-script/typescript-transformer-append-js-extension": 70,
    "@bukio/ckeditor5-media-embed": 70,
    "@bullcode/core": 69,
    "@buggyorg/library-specification": 67,
    "@builder-plugins/svg-visualize": 67,
    "@buggyorg/library-cli": 66,
    "@builderx/icons": 66,
    "@buildmotion/core": 66,
    "@builtopen/react-phone-input-2": 65,
    "@buidlhub/buidlhub-ens-notifications": 64,
    "@build-chores/babel-preset": 64,
    "@buildium/angular-walkme": 62,
    "@bufferapp/publish-two-factor-auth": 61,
    "@bug-catch/server": 61,
    "@build-chores/eslint-config-lint": 61,
    "@buggyorg/library-fileserver": 59,
    "@builder-plugins/core": 59,
    "@bukalapak/pompeii": 59,
    "@builderx/tab-view": 58,
    "@buildmotion/logging": 56,
    "@bukio-dev/test": 56,
    "@bukio/card-editor": 56,
    "@bugsplat/js-api-client": 55,
    "@building-blox/blox": 55,
    "@bullhorn/connect": 54,
    "@buggyorg/muxcontinuations": 52,
    "@bughiding/mongoose-paginate": 52,
    "@bugui/vue": 52,
    "@bugsounet/alexa": 51,
    "@build-chores/staged": 51,
    "@bugbearr/escapejsstring": 50,
    "@buggyorg/library-client": 50,
    "@bug-catch/browser": 49,
    "@building-block/idl-domexception": 49,
    "@buildit/illuminate-systems": 49,
    "@builder.io/html2canvas": 48,
    "@build-chores/commitlint": 46,
    "@builder.io/fiddle": 46,
    "@buildit/twig-api-wrapper": 46,
    "@buggyorg/nitro": 44,
    "@bughiding/onenet-protocol-buffer": 44,
    "@builtbyup/common": 44,
    "@builder-plugins/json-view": 43,
    "@bufferapp/resources": 42,
    "@builderx/react-native-swiper": 41,
    "@bulerias-org/common": 41,
    "@buildnboost/headsup-notification": 40,
    "@builtbypixel/nucleus-core": 40,
    "@bufferapp/stories-metrics": 39,
    "@bugui/shared": 39,
    "@buildlyio/freyja-react": 39,
    "@bullhorn/highland-config": 39,
    "@bullhorn/highland-components": 38,
    "@bugfix2019/utils": 37,
    "@bullhorn/highland-core": 37,
    "@build-tracker/builds": 35,
    "@builder.io/worker-env": 35,
    "@builder.io/plugin-algolia": 34,
    "@buildit/storybook-addon-info": 34,
    "@bullhorn/highland-jobs": 34,
    "@bullhorn/highland-profile": 34,
    "@bullhorn/highland-shifts": 33,
    "@buggyorg/library-mongo": 32,
    "@build-chores/test": 32,
    "@bullhorn/prettier-config": 30,
    "@builder.io/gatsby-transform-images": 29,
    "@builder.io/plugin-shopify-demo": 28,
    "@bukalapak/express-bearer-token": 28,
    "@bugfix/mobiledoc-kit": 27,
    "@buggyorg/checker": 27,
    "@bughiding/dayjs": 27,
    "@bukharim96/ress": 27,
    "@bulgamart/registro-br-isavail": 27,
    "@bugaboo/babel-plugin-mobx-deep-action": 26,
    "@builtioflow/cli-sdk": 26,
    "@buji405/complete-me": 26,
    "@bugbearr/ie11support": 25,
    "@buggyorg/graphify-react": 25,
    "@bukio/ckeditor5-angular": 25,
    "@bugbearr/encodepercent": 24,
    "@build-security/opa-express-middleware": 24,
    "@builder.io/app-context": 24,
    "@bukunmikuti/hello": 24,
    "@bugix/ngx-accordion": 22,
    "@bukio/elements": 21,
    "@bull.fm/bull": 21,
    "@bugbirdco/vue-harmony": 20,
    "@buggyorg/decompoundify": 20,
    "@buggyorg/mp-types": 20,
    "@buildtip/runsc": 20,
    "@buildtip/web-project-starter": 20,
    "@bulletyuan/tool": 20,
    "@bugbearr/hello-cli": 19,
    "@bugsounet/buffertowav": 19,
    "@bugsounet/freebox": 19,
    "@buidlers/react-scripts-template": 19,
    "@buildit/ds-demo-lib": 19,
    "@bukunmikuti/view-router": 19,
    "@bul/pool": 19,
    "@build-tracker/webpack-plugin": 18,
    "@bukio/ngx-quill": 18,
    "@bugbearr/deepcopy": 17,
    "@bugbearr/parseurisimple": 17,
    "@buggyorg/thunk-if": 17,
    "@bugsplat/ngx-charts": 17,
    "@buildmotion/actions": 17,
    "@buildo/corsproxy": 17,
    "@bulerias-org/react-common": 16,
    "@buggyorg/jsedn": 15,
    "@buildium/angular-launchdarkly-client": 15,
    "@buganto/client": 14,
    "@buganto/hh": 14,
    "@builder.io/console-feed": 14,
    "@bulma-partials/base-helpers": 14,
    "@buggyorg/delinkify": 13,
    "@buggyorg/typesystem": 13,
    "@bugsounet/native-sound": 13,
    "@bukhalo/prettier-config": 13,
    "@buganto/st": 12,
    "@buggyorg/dynatype": 12,
    "@builderbox/core": 12,
    "@builderbox/logger": 12,
    "@buildertrend/eslint-plugin-enterprise-extras": 12,
    "@builton/gatsby-source-builton": 12,
    "@bukn/eslint-config": 12,
    "@bukn/utils": 12,
    "@bullcode/react-native-google-places-autocomplete": 12,
    "@bulletyuan/style": 12,
    "@bulma-partials/base-all": 12,
    "@bulma-partials/base-generic": 12,
    "@bulma-partials/base-minireset": 12,
    "@bulma-partials/components-all": 12,
    "@bulma-partials/components-breadcrumb": 12,
    "@bulma-partials/components-card": 12,
    "@bufferapp/ui-template": 11,
    "@bughiding/echarts-gl": 11,
    "@bughiding/hello-npm": 11,
    "@bugmug/recorder": 11,
    "@bugsounet/api-freebox4g": 11,
    "@bugsounet/assistant": 11,
    "@bugsplat/ngx-datatable": 11,
    "@build-tracker/bin": 11,
    "@build774/msgpack-bigint": 11,
    "@builder.io/monaco-editor-webpack-plugin": 11,
    "@builderx/center-wrapper": 11,
    "@buildmotion/rules-engine": 11,
    "@buildpkg/cli": 11,
    "@buji/tsconfig": 11,
    "@bukio/ckeditor5-build-classic": 11,
    "@bukolajimoh/node-tsc": 11,
    "@bulbacode/rumble-lib": 11,
    "@bulgarianhealer/preload-webpack-plugin": 11,
    "@bullhorn/connexys-icons": 11,
    "@bullhorn/eslint-plugin-bullhorn": 11,
    "@bullhorn/linguist": 11,
    "@bulliby/vue-draggable": 11,
    "@bully-swap/bully-swap-core": 11,
    "@bully-swap/sdk": 11,
    "@bully-swap/uikit": 11,
    "@bullzer/cordova-plugin-emdkscanner": 11,
    "@buggyorg/dynatype-translator-graph": 10,
    "@buhta-ooo/graphql": 10,
    "@builder.io/app-plugin-demo": 10,
    "@bulentv/pkg": 9
}