{
    "@bitauth/libauth": 15677,
    "@biotope/quality-gate": 5085,
    "@bitblit/ratchet": 3727,
    "@bitblit/epsilon": 2361,
    "@bingoit/desktop-ui": 2186,
    "@bingoit/desktop-form": 2102,
    "@bingoit/desktop-flow": 2089,
    "@bingoit/desktop-base": 2076,
    "@bitcapital/base-sdk": 1803,
    "@bitcapital/core-sdk": 1668,
    "@bios21/tstrait": 1622,
    "@bingoit/business-rules": 1599,
    "@bitcapital/shared-sdk": 1441,
    "@binxhealth/pino-stackdriver": 1390,
    "@biomedit/next-widgets": 1331,
    "@bitblit/saltmine": 1277,
    "@bingo_soft/mapmanager": 1071,
    "@bitcapital/ccs-sdk": 1059,
    "@bitcapital/positional-parser": 998,
    "@bitclu-inc-staging/base2": 986,
    "@bingoit/mobile-ui": 901,
    "@bingoit/mobile-form": 889,
    "@biproxi/react-text-mask": 879,
    "@bitbloq/borndate": 821,
    "@biotope/build": 816,
    "@bipsync/apiclient": 770,
    "@bingoit/mobile-base": 706,
    "@biscuit-store/core": 683,
    "@biowonks/aseq": 667,
    "@bingoit/mobile-flow": 658,
    "@bipsync/ews-javascript-api": 590,
    "@bingo_soft/dsl-builder": 572,
    "@birchill/hikibiki-data": 566,
    "@biryudumkitap/localization": 564,
    "@bingoit/form": 539,
    "@bindable-ui/bindable": 535,
    "@bitclave/base-client-js": 531,
    "@biotope/resource-loader": 527,
    "@biscuitpants/codemirror-spell-checker": 516,
    "@biscuit-store/react": 514,
    "@biotope/element": 507,
    "@biproxi/utils": 484,
    "@birchill/json-equalish": 470,
    "@biscuit-store/adapter": 470,
    "@bioxydyn/dicom-parser": 444,
    "@biproxi/models": 444,
    "@biscuit-store/types": 444,
    "@bingoit/utils": 440,
    "@binssoft/ngx-captcha": 433,
    "@biothings-explorer/smartapi-kg": 425,
    "@bingoit/ajax": 421,
    "@birdeatsbug/vue-cli-plugin-browser-extension": 417,
    "@bitbar/cloud-api-client": 410,
    "@bioinsilico/rcsb-saguaro-app": 408,
    "@birchill/normal-jp": 392,
    "@birdeatsbug/vue-cli-plugin-apollo": 389,
    "@bingoit/flow": 375,
    "@biothings-explorer/call-apis": 371,
    "@bingoit/dingtalk": 367,
    "@binarycapsule/ui-capsules": 358,
    "@binpar/mupx": 319,
    "@bitacode/apispecmd-ts": 276,
    "@biothings-explorer/query_graph_handler": 267,
    "@birdseye/app": 250,
    "@birman/babel-plugin-auto-css-modules": 240,
    "@biotic-ui/std": 239,
    "@birman/babel-preset-birman": 238,
    "@birman/utils": 234,
    "@binaryprovider/charlatan": 229,
    "@biothings-explorer/api-response-transform": 222,
    "@bioinsilico/rcsb-saguaro": 210,
    "@birdseye/vue": 208,
    "@bindable-ui/bindable-icons": 200,
    "@biotope/generator": 200,
    "@bitblit/paratrade-common": 194,
    "@birdseye/core": 191,
    "@biowasm/aioli": 185,
    "@biotope/configuration": 184,
    "@binder/ui": 180,
    "@bitboss/game-integration": 179,
    "@biowaffeln/next-linaria": 178,
    "@bincode/jekpack": 173,
    "@binpar/jest-gql": 173,
    "@birdbrain/typeorm-seeder": 171,
    "@bingoit/ding-biz-rule": 167,
    "@bip-sh/cli": 161,
    "@bisaek/is": 149,
    "@biothings-explorer/json-transformer": 147,
    "@bingosoftnn/vue-treeselect": 146,
    "@biorate/collection": 139,
    "@biotic-ui/context-menu": 138,
    "@biotic-ui/input": 138,
    "@bitbite/datepicker-plus": 138,
    "@biotic-ui/drawer": 136,
    "@biotic-ui/bottom-sheet": 133,
    "@biotic-ui/dialog": 133,
    "@biotic-ui/stepper": 133,
    "@biotope/cli": 129,
    "@biothings-explorer/explain": 127,
    "@biotic-ui/layout": 126,
    "@biotic-ui/menu": 119,
    "@bitbite/filtered-list": 118,
    "@biorate/errors": 116,
    "@birramos/core": 114,
    "@bionikspoon/react-toolbox": 113,
    "@biorate/symbolic": 113,
    "@bingoit/dingtalk-sync": 112,
    "@binomio/webcomponents": 112,
    "@biotope/preview": 111,
    "@biotic-ui/notification": 109,
    "@bingsjs/op-lint-staged": 104,
    "@bitbar/finka": 104,
    "@bingsjs/op-depcruise": 102,
    "@bingsjs/op-tools": 102,
    "@biorate/tools": 101,
    "@bingsjs/op-commitizen": 100,
    "@bingsjs/op-commitlint": 100,
    "@bingsjs/op-husky": 100,
    "@bingsjs/op-jest": 100,
    "@bingsjs/op-lint": 100,
    "@bingsjs/op-tscdoc": 99,
    "@biptik/apollo": 99,
    "@bingo347/eslint-config": 97,
    "@biotic-ui/tabs": 97,
    "@bingumd/itcss-objects": 96,
    "@bingumd/utils": 95,
    "@biovision/biovision": 91,
    "@bipcon/packshotapi": 89,
    "@bitblit/ports-of-call": 88,
    "@bitclu-inc-staging/validation1": 85,
    "@biotic-ui/leptons": 84,
    "@biotic-ui/collapsible": 83,
    "@bingsjs/ts-std-tools": 81,
    "@binbobo/my-table": 80,
    "@bingsjs/ts-lerna-std-tools": 79,
    "@birdseye/snapshot": 79,
    "@bitbeat/core": 77,
    "@biryani/core": 76,
    "@bitberry/bankai-revolutions-pagecomponents-goldbach": 75,
    "@binaryfissiongames/twitch-webhooks": 74,
    "@bitaccess/coinlib-bitcoin": 74,
    "@bitaccess/coinlib-litecoin": 74,
    "@biotic-ui/select": 73,
    "@biosci/common": 72,
    "@bionikspoon/react-scripts": 71,
    "@bitaccess/coinlib-bitcoin-cash": 71,
    "@bitaccess/coinlib-doge": 71,
    "@bingoit/cms-common": 70,
    "@bipcon/packshotdbservice": 68,
    "@bitaccess/coinlib": 68,
    "@bitcoin-api.io/common-private": 68,
    "@bitacode/tokenator": 67,
    "@biotic-ui/button": 66,
    "@bitbeat/web": 66,
    "@binder/editor": 65,
    "@bishwenduk029/fringe": 65,
    "@bingbing_zhao/xc-ui": 63,
    "@biscuitech/eslint-config": 63,
    "@birpal/circle": 61,
    "@biot-dev/event-bus-client": 60,
    "@bitboss/tokenized": 60,
    "@bindle/library": 58,
    "@binier/hygen": 58,
    "@bingoit/cms-desktop": 57,
    "@bingumd/sass-utils": 57,
    "@biptik/environment": 57,
    "@bingo347/fn": 56,
    "@biodiversity/ecosystem-style": 56,
    "@biohuns/min2phase": 56,
    "@bitbite/cqrs": 56,
    "@bitcoin-api.io/common-exchange": 56,
    "@bincode/storybook": 55,
    "@birchill/bugsnag-zero": 55,
    "@biodiversity/vue-authentication": 53,
    "@bionicmetrics/bionic": 53,
    "@binarycapsule/editor": 51,
    "@binwus-org/onvif-nvt": 51,
    "@binssoft/ngx-loader": 50,
    "@biopolymer-elements/bio-link": 49,
    "@biodiversity/ecosystem-tokens": 47,
    "@birman/core": 47,
    "@bitauth/react-scripts-bitauth-ide": 47,
    "@binogi/angucomplete-alt-es6": 45,
    "@birman/ast": 45,
    "@bitbeat/websocket": 45,
    "@bitblit/schmocha": 45,
    "@bingosoft/cli": 44,
    "@bingumd/itcss-utility": 44,
    "@bingumd/stylelint-config": 44,
    "@bitbeat/redis": 43,
    "@bioinsilico/rcsb-saguaro-3d": 42,
    "@birman/types": 42,
    "@bitclu-inc-staging/tooltip2": 42,
    "@binpar/epub3-parser": 41,
    "@biosimulations/status-page": 41,
    "@biossun/nami": 40,
    "@biotic-ui/icon": 39,
    "@biotic-ui/sortable": 39,
    "@biscuitfarm/uikit": 39,
    "@bitaccess/coinlib-ripple": 39,
    "@bitaccess/coinlib-stellar": 39,
    "@bitchcraft/injector": 39,
    "@bingumd/itcss-generic": 38,
    "@biodiversity/ecosystem-icons": 38,
    "@biotic-ui/text": 38,
    "@birman/error-code-map": 38,
    "@bit3x/search-community": 38,
    "@bitaccess/coinlib-common": 38,
    "@binarysearch/dashboard": 37,
    "@bird.io/nuxt": 37,
    "@bitaccess/coinlib-tron": 37,
    "@bingumd/itcss-elements": 36,
    "@bintur_rasheed/lotide": 36,
    "@biothings-explorer/annotator": 36,
    "@bipcon/packshotpdfservice": 36,
    "@bitaccess/coinlib-ethereum": 36,
    "@binbobo/comps": 35,
    "@binquant/heart-client": 35,
    "@binzy/simple": 35,
    "@bionikspoon/html-to-md": 35,
    "@biostudies/ckeditor5-build-balloon": 35,
    "@birdman_jp/dollar-request": 35,
    "@biotic-ui/panel": 34,
    "@bird.io/client": 34,
    "@bird.io/server": 34,
    "@bishoy_melek_wadie/s3_image_uploader": 34,
    "@bitalikrty/react-native-tools": 34,
    "@bincode/infinite-gallery": 33,
    "@biqi/ui": 33,
    "@bit/bundler": 33,
    "@binarycapsule/test-package": 32,
    "@binbobo/my-cli": 32,
    "@binquant/message-client": 32,
    "@birman/test": 32,
    "@bitalikrty/mixit": 32,
    "@bincode/circle-progress": 31,
    "@bindoc/templates": 31,
    "@bingumd/itcss-tools": 31,
    "@binnovative/ngx-list": 31,
    "@biocad/jfw": 31,
    "@biodiversity/logger": 31,
    "@biosoftcl/chart-js-module": 31,
    "@birksy89/gatsby-theme-events": 31,
    "@birman/bundler-utils": 31,
    "@biopolymer-elements/bio-pdb": 30,
    "@biopolymer-elements/bio-pubmed": 30,
    "@biotope/core": 30,
    "@bipcon/registerservice": 30,
    "@birman/bundler-webpack": 30,
    "@binarymuse/cmark": 29,
    "@binquant/message-core": 29,
    "@bionikspoon/react-dev-utils": 29,
    "@biosoftcl/open-layers-module": 29,
    "@biproxi/react-pdf": 29,
    "@bindr/bindr": 28,
    "@biossun/react-view": 28,
    "@birdbrain/nest-typeorm-seeder": 28,
    "@bitclave/bitclave-ui": 28,
    "@bitcode-solutions/styles": 28,
    "@binogi/es6-angular-moment": 27,
    "@biscottino/store": 27,
    "@bit/bundler-utils": 27,
    "@binarymuse/probot": 26,
    "@binhlv/add": 26,
    "@binhlv/print": 26,
    "@biodiversity/ssr-breakpoints": 26,
    "@biossun/color": 26,
    "@biothings-explorer/expander": 26,
    "@biotic-ui/db": 26,
    "@biotic-ui/floating-task-bar": 26,
    "@biotope/pwa": 26,
    "@birchill/hikibiki-sync": 26,
    "@biscottino/session": 26,
    "@bishopcais/discover": 26,
    "@bistrohub/hub-v2": 26,
    "@bit/loader": 26,
    "@binarysearch/crud-tables": 25,
    "@bincode/fixed-image": 25,
    "@bindr/cli": 25,
    "@bingpo/table": 25,
    "@biopolymer-elements/bio-mygene": 25,
    "@bipolar/meta": 25,
    "@bindoc/table": 24,
    "@biotic-ui/boson": 24,
    "@biowaffeln/next-gen": 24,
    "@bit/loader-babel": 24,
    "@bitchcraft/unicorn-logger": 24,
    "@binhlv/multiply": 23,
    "@bipolar/node": 23,
    "@bisvarup/react-read-more": 23,
    "@biopolymer-elements/bio-mygene-search": 22,
    "@biotope/build-plugin-hbs": 22,
    "@biscottino/memory-store": 22,
    "@biscottino/mongo-store": 22,
    "@bit/bundler-splitter": 22,
    "@binssoft/ngx-dialogs": 21,
    "@binur95/eslint-config-react": 21,
    "@biodiversity/eco-molecule-add-to-calendar": 21,
    "@biohumanetics/auth0-utils": 21,
    "@biomart/auth-proxy": 21,
    "@biomart/http-matcher": 21,
    "@bipcon/orderservice": 21,
    "@bipinpaulbedi/paul-blog-typography-theme": 21,
    "@bishopcais/cog-cli": 21,
    "@bitaffair/bift": 21,
    "@biopolymer-elements/bio-icons": 20,
    "@biovision/comunit": 20,
    "@bitanxen/react-datatable": 20,
    "@bitbrother/fetch-dog-hooks": 20,
    "@binderpos/react-currency": 19,
    "@binpar/graphql-schema-typescript": 19,
    "@binyamin/lincoln": 19,
    "@binzume/aframe-vrm": 19,
    "@biopolymer-elements/bio-interpro": 19,
    "@bishoy_melek_wadie/react-admin-firebase": 19,
    "@bit/bundler-minifyjs": 19,
    "@bitbloq/ui": 19,
    "@bingoit/mobile-sorting": 18,
    "@binno/core": 18,
    "@bioenrichment/ldf-client": 18,
    "@biojs/generator-biojs-webcomponents": 18,
    "@biopolymer-elements/bio-pathways": 18,
    "@biqpete/ch97159": 18,
    "@birdman_jp/webpack-spritesmith": 18,
    "@bitarray/typedarray": 18,
    "@bitbond/components": 18,
    "@bitbybit/configurable": 18,
    "@binded/verify-proof": 17,
    "@binpar/tsv-to-issues": 17,
    "@binquant/message-server": 17,
    "@binur95/eslint-config": 17,
    "@binur95/eslint-config-babel": 17,
    "@binyamin/data-cache": 17,
    "@biopolymer-elements/bio-go": 17,
    "@biopolymer-elements/bio-mygene-fields": 17,
    "@biopolymer-elements/bio-mygene-info": 17,
    "@bipcon/objectstoreapi": 17,
    "@biptik/cookie": 17,
    "@bitaffair/bift-jwt": 17,
    "@bindoc/loading": 16,
    "@biodiversity/generics": 16,
    "@biomath-421/npx-card": 16,
    "@biotope/storybook-addon-compiled-code": 16,
    "@biovision/votes": 16,
    "@biptik/state": 16,
    "@bird.io/session": 16,
    "@bit/loader-httpresource": 16,
    "@bit/loader-shimmer": 16,
    "@bitchcraft/keyconst": 16,
    "@bitchcraft/ocake": 16,
    "@bitclu-inc-staging/chronos1": 16,
    "@biodiversity/helpers": 15,
    "@biqdev/angularjs-colorpicker": 15,
    "@biscuitfarm/eslint-config-biscuit": 15,
    "@bit/loader-css": 15,
    "@bit/loader-eslint": 15,
    "@bit/loader-js": 15,
    "@bit/loader-sourcemaps": 15,
    "@bitchin/react-material-web": 15,
    "@bitclu-inc-staging/positioning1": 15,
    "@bitcoin-api.io/common-general": 15,
    "@binarysearch/ng-socket": 14,
    "@binarystorms/mood_expressions_models": 14,
    "@bingoit/ams-desktop": 14,
    "@biodiversity/connections": 14,
    "@biohumanetics/get-ssm-by-path": 14,
    "@biomedia-nl/react-native-material-kit": 14,
    "@biovision/posts": 14,
    "@bit/bundler-extractsm": 14,
    "@bit/loader-builtins": 14,
    "@bit/loader-cache": 14,
    "@bit/loader-json": 14,
    "@bit/loader-remove": 14,
    "@bitaffair/levars-server": 14,
    "@bitberry/httpserver": 14,
    "@bitbloq/lib3d": 14,
    "@bitbrother/okey": 14,
    "@binarytales/noopone": 13,
    "@binarytales/nooptwo": 13,
    "@bine/test": 13,
    "@binno/components": 13,
    "@binomio/csv-exporter": 13,
    "@binomio/ig-api": 13,
    "@binpar/react-native-geocoder": 13,
    "@binssoft/multi-uploader": 13,
    "@biodiversity/http-responses": 13,
    "@bioenrichment/xrefdb-client": 13,
    "@biohumanetics/ns-call-restlet": 13,
    "@bioruebe/eslint-config": 13,
    "@biothings-explorer/transform-api-response": 13,
    "@biotope/build-plugin-iconfont": 13,
    "@biovision/comments": 13,
    "@bit-vision/indexer": 13,
    "@bit/bundler-banner": 13,
    "@bitaffair/hapi-routes": 13,
    "@bitaffair/levars-client": 13,
    "@bitbloq/3d": 13,
    "@bitbrother/stringer": 13,
    "@bitbybit/amp": 13,
    "@bitclu-inc-staging/utils1": 13,
    "@bitcode-solutions/components": 13,
    "@bitcog/recursive-readdir": 13,
    "@binarycapsule/ui-caps": 12,
    "@binarymuse/relay-compiler": 12,
    "@binarymuse/tsmonad": 12,
    "@bincode/wheel-manager": 12,
    "@bing107/utils": 12,
    "@binguo/weapp": 12,
    "@binpar/react-native-calendar": 12,
    "@binpar/react-native-swipeout": 12,
    "@binur95/eslint-config-typescript": 12,
    "@biodiversity/calendar": 12,
    "@biorz/cli": 12,
    "@biosimulations/hdf5apiclient": 12,
    "@biothings-explorer/biothings_explorer_test_toolkit": 12,
    "@bipcon/pdfitemapi": 12,
    "@bird-cage/number-formatter": 12,
    "@biruk/react-simple-format": 12,
    "@bisquit/vue-router-composable": 12,
    "@bit/loader-text": 12,
    "@bitbybit/amp-message": 12,
    "@bitbybit/emitter": 12,
    "@bingjian.guo/falcon-core": 11,
    "@binoyzone/tiny": 11,
    "@biocad/biocad": 11,
    "@bisect/bisect-core-ts": 11,
    "@bitalikrty/redux-create-reducer": 11,
    "@bitbrother/fetch-dog": 11,
    "@binbomb/binbomb": 10,
    "@binhlv/plus": 10,
    "@biota/builder": 10,
    "@birjik/npmmoduletest": 10,
    "@bit-weavers/docker-host-name": 10,
    "@bit/loader-excludes": 10,
    "@bit/loader-extensions": 10,
    "@bitbar/owasp-unsafe-passwords": 10,
    "@bitbloq/bloqs": 10,
    "@binarysearch/lib2": 9,
    "@binbomb/my-vue-library": 9,
    "@binch-solutions/epson-epos-printer": 9,
    "@binglu/yytrain": 9,
    "@bingneef/react-optimize": 9,
    "@binoalien/node-digest-auth-client": 9,
    "@binujaya/hello-npm": 9,
    "@binyamin/markdown-it-wikilinks": 9,
    "@biodiversity/eco-molecule-calendar-vue": 9,
    "@bioenrichment/config": 9,
    "@biokiste/react-components": 9,
    "@bipcon/productservice": 9,
    "@bipink25/tiny": 9,
    "@biptik-test-scope/apollo": 9,
    "@biptik/i18n": 9,
    "@biptik/lagertha-font": 9,
    "@biptik/lagertha-globals": 9,
    "@biptik/sapper": 9,
    "@biqdev/jquery-flot-typing": 9,
    "@birhane/fni-tradein": 9,
    "@birhane/ratesandresidual": 9,
    "@birjik/rn-apple-healthkit": 9,
    "@birman/babel-plugin-utils": 9,
    "@bitalikrty/test": 9,
    "@bitbrother/flash-splash": 9,
    "@bitcoin-api.io/backend-common-utilities": 9,
    "@bitcoin-api.io/common-bridge": 9,
    "@binarysearch/lib1": 8,
    "@bingchang/hello-wasm": 8,
    "@bingumd/postcss-utils": 8,
    "@binhdt62003/myextension": 8,
    "@biniek-io/hello-wasm": 8,
    "@binoy14/react-scripts": 8,
    "@binyfe/biny-npm": 8,
    "@biodataanalysis/thrift-trunk": 8,
    "@biofabrik/wastx-machine-server-shared": 8,
    "@biokube/integration": 8,
    "@biomath-421/mb-holidates": 8,
    "@biothings-explorer/id_resolver": 8,
    "@birax/hookis": 8,
    "@birdeatsbug/console-feed": 8,
    "@birdiecare/rrule-tz": 8,
    "@birdiedata/butils": 8,
    "@birdyboy18/contentful-hugo": 8,
    "@biruk/react-images": 8,
    "@biruk/react-scrolllock": 8,
    "@birwin/notable-lib": 8,
    "@bishopcais/cog-loader": 8,
    "@bit-wrangler/dom-nav": 8,
    "@bitalikrty/codes": 8,
    "@bitbar/deferred-promise": 8,
    "@bitbloq/hardware-designer": 8,
    "@bitbloq/junior": 8,
    "@bitbonsai/gitremote": 8,
    "@bitbounti-oss/tangly": 8,
    "@bitch2k/uikit": 8,
    "@bitchcraft/timestamp": 8,
    "@binwus-org/reverse-tunnel-ssh": 7,
    "@bisudev/bisu-react-modal": 7
}